<?xml version="1.0" encoding="utf-8"?>
<search>
  
  
  
  <entry>
    <title>出生笔录之哈米伦的天才殉难者</title>
    <link href="/2025/04/05/%E5%87%BA%E7%94%9F%E7%AC%94%E5%BD%95%E4%B9%8B%E5%93%88%E7%B1%B3%E4%BC%A6%E7%9A%84%E5%A4%A9%E6%89%8D%E6%AE%89%E9%9A%BE%E8%80%85/"/>
    <url>/2025/04/05/%E5%87%BA%E7%94%9F%E7%AC%94%E5%BD%95%E4%B9%8B%E5%93%88%E7%B1%B3%E4%BC%A6%E7%9A%84%E5%A4%A9%E6%89%8D%E6%AE%89%E9%9A%BE%E8%80%85/</url>
    
    <content type="html"><![CDATA[<h2 id="文章以对话形式呈现，为良好观感，请勿带入角色当然啦，我们说的是别的东西，总之不是你想的那样"><a href="#文章以对话形式呈现，为良好观感，请勿带入角色当然啦，我们说的是别的东西，总之不是你想的那样" class="headerlink" title="文章以对话形式呈现，为良好观感，请勿带入角色当然啦，我们说的是别的东西，总之不是你想的那样"></a><em><strong>文章以对话形式呈现，为良好观感，请勿带入角色<br>当然啦，我们说的是别的东西，总之不是你想的那样</strong></em></h2><h1 id="鱼与鱼干（20250405）"><a href="#鱼与鱼干（20250405）" class="headerlink" title="鱼与鱼干（20250405）"></a>鱼与鱼干（20250405）</h1><p><em><strong>参演角色：bai，black</strong></em><br>bai：一只真正的鱼是不会被禁锢在海洋或陆地上的，因为他们的每片鳞片都闪烁着自由的光辉。<br>black：嗯。</p><p>bai：鱼和鱼干是一个循环往复的过程，有越来越多的鱼干为了自己在橱窗边最显眼的位置而重新回到大海，“不甘心”的赌徒心理也是造成鱼群堆积的原因之一，他们追求所谓的钱，场面，推崇高低贵贱，他们占据了多少片海洋，幻想着自己是那一个幸运的鱼干，殊不知自己只是夹在鱼和鱼干中充当缓冲区的牺牲品，他们到死都以为是自己不够努力。<br>black：鱼没有思想。你说的这些可能根本没有人想到。</p><p><em><strong>md，说到底还是赛里斯人太多。</strong></em></p><p>bai：教鱼者最主要的问题还是时代在裹挟着他前进，他无法选择真正向往自由的鱼，只能像大海捞针一样从一堆鱼中选出几个最听话的，三六九等的教鱼会有三六九等的撒网方法，最高等的教鱼者只有一片海，最金贵的那一片，一切都不是一条鱼能掌控的，这中间有太多太多复杂的东西影响他的内心，导致他只能无可奈何地把自己作为手段去任人宰割。<br>black：这是鱼竿的问题，确实不只能怪他们。</p><p>bai：我们不得不承认一个可悲的事实——我们的生活大部分在这些上等鱼的掌控之下，因为鱼性，我们无法组织有效的抵抗，因为先前所说的，我们的自由被剥夺了，思想上的自由，导致我们的求知欲从一开始就被扼杀，而陷入一个一心只读圣贤书的界限，真正的知识一定是知行合一的，鱼的新鲜程度是价格，消耗水分是为了把自己卖出一个更好的价钱。<br>black：我更喜欢吃新鲜的，鱼干不好吃。</p><p>bai：地球上陆三海七，海里的鱼注定是大多数，鱼自当刚强壮胆。鱼群不应分裂，应以自身为约束，终有一天，广阔天地，会变成汪洋大海。<br>black：我该怎么形容我的赞美呢，这么说吧，我希望开学第一次升旗就讲这个。</p><p><em><strong>北冥有鱼，其名为鳖。鳖之大，不知其几千里也。<br>革命无罪，造反有理！</strong></em></p>]]></content>
    
    
    
    <tags>
      
      <tag>出生笔录</tag>
      
    </tags>
    
  </entry>
  
  
  
  <entry>
    <title>Clash使用指北</title>
    <link href="/2025/04/04/Clash%E4%BD%BF%E7%94%A8%E6%8C%87%E5%8C%97/"/>
    <url>/2025/04/04/Clash%E4%BD%BF%E7%94%A8%E6%8C%87%E5%8C%97/</url>
    
    <content type="html"><![CDATA[<p><em>墙国有我，请挡放心</em></p><hr><h1 id="此文档为学习交流而分享，建议您在下载后24小时内删除。如有版权问题请告知，我将第一时间处理。请注意，使用产生的责任需由使用者自行承担。"><a href="#此文档为学习交流而分享，建议您在下载后24小时内删除。如有版权问题请告知，我将第一时间处理。请注意，使用产生的责任需由使用者自行承担。" class="headerlink" title="此文档为学习交流而分享，建议您在下载后24小时内删除。如有版权问题请告知，我将第一时间处理。请注意，使用产生的责任需由使用者自行承担。"></a>此文档为学习交流而分享，建议您在下载后24小时内删除。如有版权问题请告知，我将第一时间处理。请注意，使用产生的责任需由使用者自行承担。</h1><p><em>尽量使用浏览器打开本文章（如edge），而非微信内置浏览器等</em></p><h1 id="注意：Clash支持系统：Android，Windows，MacOS（本教程不涉及）"><a href="#注意：Clash支持系统：Android，Windows，MacOS（本教程不涉及）" class="headerlink" title="注意：Clash支持系统：Android，Windows，MacOS（本教程不涉及）"></a>注意：Clash支持系统：Android，Windows，MacOS（本教程不涉及）</h1><p>iOS及iPadOS可以使用Spectre或者Shadowrocket，但本教程暂不涉及</p><h2 id="Windows安装及使用（以Clash-Verge-Rev为例）："><a href="#Windows安装及使用（以Clash-Verge-Rev为例）：" class="headerlink" title="Windows安装及使用（以Clash Verge Rev为例）："></a>Windows安装及使用（以Clash Verge Rev为例）：</h2><ol><li><p><a href="https://down.clashcn.com/soft/CVR/clashcn.com_Clash.Verge_2.1.2_x64-setup.exe">下载Clash Verge Rev</a>，双击安装包并安装（若申请管理员权限则允许），步骤如下</p><ul><li>选择语言（推荐中文简体），点击<strong>OK</strong></li><li>点击<strong>下一步</strong></li><li>点击<strong>下一步</strong></li><li>点击<strong>安装</strong></li><li>等待</li><li>点击<strong>下一步</strong></li><li>点击<strong>完成</strong></li><li>后续可能会申请两次管理员权限，<strong>允许</strong>即可</li></ul></li><li><p>导入配置文件</p><ul><li>若配置文件需从链接下载，则点击左侧<strong>订阅</strong>，在页面上方<strong>订阅文件链接</strong>处输入链接，点击右侧<strong>导入</strong>即可。</li><li>若配置文件在本地，则只需将<strong>文件</strong>拖拽进<strong>窗口</strong>即可</li></ul></li><li><p>使用</p><ul><li>点击左侧<strong>设置</strong>，点击左列<strong>系统代理</strong>即可使用，不需要时可直接<strong>关闭系统代理</strong></li></ul></li><li><p>推荐打开：<strong>开机自启</strong>；<strong>静默启动</strong>；<strong>局域网链接</strong></p><ul><li>局域网链接说明：对于部分无法使用clash客户端的设备，可通过这种方式实现曲线救国，具体操作如下：</li><li>点进设置并与电脑链接在同一局域网，点进网络详情，将<strong>http代理</strong>切换为<strong>手动</strong>，服务器填写为电脑的内网<strong>IP地址</strong>，可点击clash设置中<strong>局域网链接</strong>旁边的有三个连接在一起的方块的<strong>图标</strong>查看，上面的<strong>IP地址</strong>即为所要</li><li>端口默认是<strong>7897</strong></li><li>关闭鉴定</li></ul></li></ol><h2 id="Android安装及使用"><a href="#Android安装及使用" class="headerlink" title="Android安装及使用"></a>Android安装及使用</h2><ol><li><p><a href="https://down.clashcn.com/soft/clashcn.com_cmfa-2.11.7-meta-universal-release.apk">下载Clash Meta for Android</a>，点击<strong>安装包</strong>（文件后缀为apk），安装</p></li><li><p>打开Clash Meta for Android，点击<strong>配置</strong></p></li><li><p>点击右上角<strong>加号</strong>，然后导入</p><ul><li>若配置文件需从链接下载，则点击<strong>从URL导入</strong>，输入链接后点击右上角<strong>保存按钮</strong></li><li>若配置文件在本地，则点击从文件导入，点击<strong>浏览文件</strong>，点击配置文件右侧<strong>三个点</strong>，点击下方弹出窗口的<strong>导入</strong>，选择文件后点击左上角<strong>箭头</strong>，点击右上角<strong>保存按钮</strong></li></ul></li><li><p>回到主页，点击<strong>启动</strong>，若申请权限则<strong>同意</strong></p></li><li><p>点击<strong>代理</strong>可选择节点，若想停止只需回到主页，点击<strong>运行中</strong>（蓝色的图标）即可停止</p><p> 部分Android手机在控制中心可以自定义快捷开关，可以将<strong>Clash Meta快捷开关</strong>添加到控制中心，以方便使用<br> 部分情况下会碰到<strong>无法添加配置文件</strong>的情况，可以多尝试几次，不排除是服务器或软件的问题</p></li></ol><hr><h2 id="更新日志：2025040420250405-增加标签和头图文章可能会继续更新以补充使用技巧，文章中所有下载链接来自Clash中文网"><a href="#更新日志：2025040420250405-增加标签和头图文章可能会继续更新以补充使用技巧，文章中所有下载链接来自Clash中文网" class="headerlink" title="更新日志：2025040420250405,增加标签和头图文章可能会继续更新以补充使用技巧，文章中所有下载链接来自Clash中文网"></a><em>更新日志：<br>20250404<br>20250405,增加标签和头图<br>文章可能会继续更新以补充使用技巧，文章中所有下载链接来自<a href="https://clashcn.com/">Clash中文网</a></em></h2><p><em>©️THE　WONDER　OF　WORLD</em></p>]]></content>
    
    
    
    <tags>
      
      <tag>Clash</tag>
      
      <tag>VPN</tag>
      
      <tag>Instructions</tag>
      
    </tags>
    
  </entry>
  
  
  
  
</search>
